{"order":{"orderId":"0000000002","product":"cantaloupes","amount":100,"orderReceived":"2025-01-31T15:38:24.0817176","orderDeliveryDate":"2025-02-03"}}{"order":{"orderId":"0000000001","product":"carrots","amount":2000,"orderReceived":"2025-01-31T15:38:24.0454376","orderDeliveryDate":"2025-02-03"}}{"order":{"orderId":"0000000005","product":"bananas","amount":750,"orderReceived":"2025-01-31T15:38:24.0837177","orderDeliveryDate":"2025-02-03"}}{"order":{"orderId":"0000000003","product":"oranges","amount":1000,"orderReceived":"2025-01-31T15:38:24.0827179","orderDeliveryDate":"2025-02-03"}}{"order":{"orderId":"0000000004","product":"apples","amount":500,"orderReceived":"2025-01-31T15:38:24.0827179","orderDeliveryDate":"2025-02-03"}}